linear_term/__init__.py
linear_term/app.py
linear_term/cli.py
linear_term/config.py
linear_term/api/__init__.py
linear_term/api/client.py
linear_term/api/models.py
linear_term/cache/__init__.py
linear_term/cache/store.py
linear_term/utils/__init__.py
linear_term/utils/editor.py
linear_term/views/__init__.py
linear_term/views/triage.py
linear_term/widgets/__init__.py
linear_term/widgets/command_palette.py
linear_term/widgets/detail_panel.py
linear_term/widgets/filter_bar.py
linear_term/widgets/help_screen.py
linear_term/widgets/issue_form.py
linear_term/widgets/issue_list.py
linear_term/widgets/kanban_view.py
linear_term/widgets/settings_panel.py
linear_term/widgets/sidebar.py
linear_term/widgets/status_bar.py
linear_term-0.1.0.dist-info/METADATA
linear_term-0.1.0.dist-info/WHEEL
linear_term-0.1.0.dist-info/entry_points.txt
linear_term-0.1.0.dist-info/licenses/LICENSE
linear_term-0.1.0.dist-info/RECORD
