Metadata-Version: 2.4
Name: linear-term
Version: 0.1.0
Summary: A terminal user interface for Linear project management
Project-URL: Homepage, https://github.com/tjburch/linear-term
Project-URL: Repository, https://github.com/tjburch/linear-term
Project-URL: Issues, https://github.com/tjburch/linear-term/issues
Author-email: Tyler Burch <burcht11@gmail.com>
License: # PolyForm Noncommercial License 1.0.0
License-File: LICENSE
Keywords: cli,linear,project-management,terminal,textual,tui
Classifier: Development Status :: 4 - Beta
Classifier: Environment :: Console
Classifier: Intended Audience :: Developers
Classifier: Operating System :: OS Independent
Classifier: Programming Language :: Python :: 3
Classifier: Programming Language :: Python :: 3.10
Classifier: Programming Language :: Python :: 3.11
Classifier: Programming Language :: Python :: 3.12
Classifier: Topic :: Software Development :: Bug Tracking
Classifier: Topic :: Utilities
Requires-Python: >=3.10
Requires-Dist: gql[httpx]>=3.5.0
Requires-Dist: httpx>=0.27.0
Requires-Dist: platformdirs>=4.0
Requires-Dist: pyyaml>=6.0
Requires-Dist: rich>=13.0
Requires-Dist: textual>=0.47.0
Provides-Extra: dev
Requires-Dist: pytest-asyncio>=0.23; extra == 'dev'
Requires-Dist: pytest>=8.0; extra == 'dev'
Requires-Dist: ruff>=0.3.0; extra == 'dev'
